ibash/__init__.py
ibash-3.0.0.dist-info/METADATA
ibash-3.0.0.dist-info/WHEEL
ibash-3.0.0.dist-info/top_level.txt
ibash-3.0.0.dist-info/RECORD
