Metadata-Version: 2.1
Name: ibash
Version: 3.0.0
Summary: Python Package made by Issam MHADHBI 
Home-page: https://gitlab.com/isampypi/ibash
Author: MhadhbiXissam
Author-email: mhadhbixissam@gmail.com
Classifier: Programming Language :: Python :: 3
Classifier: License :: OSI Approved :: MIT License
Classifier: Operating System :: OS Independent
Requires-Dist: colorama
